README.md
setup.cfg
setup.py
moneyforward_ex/__init__.py
moneyforward_ex/api_client.py
moneyforward_ex/configuration.py
moneyforward_ex/exceptions.py
moneyforward_ex/rest.py
moneyforward_ex.egg-info/PKG-INFO
moneyforward_ex.egg-info/SOURCES.txt
moneyforward_ex.egg-info/dependency_links.txt
moneyforward_ex.egg-info/requires.txt
moneyforward_ex.egg-info/top_level.txt
moneyforward_ex/api/__init__.py
moneyforward_ex/api/dept_api.py
moneyforward_ex/api/e_doc_api.py
moneyforward_ex/api/ex_destination_api.py
moneyforward_ex/api/ex_invoice_transaction_api.py
moneyforward_ex/api/ex_item_api.py
moneyforward_ex/api/ex_journal_api.py
moneyforward_ex/api/ex_office_member_setting_api.py
moneyforward_ex/api/ex_report_api.py
moneyforward_ex/api/ex_report_unit_api.py
moneyforward_ex/api/ex_transaction_api.py
moneyforward_ex/api/excise_api.py
moneyforward_ex/api/mf_file_api.py
moneyforward_ex/api/office_api.py
moneyforward_ex/api/office_member_api.py
moneyforward_ex/api/position_api.py
moneyforward_ex/api/project_code_api.py
moneyforward_ex/models/__init__.py
moneyforward_ex/models/attendant.py
moneyforward_ex/models/bank.py
moneyforward_ex/models/bank_branch.py
moneyforward_ex/models/dept.py
moneyforward_ex/models/dept_input.py
moneyforward_ex/models/e_doc_meta_datum.py
moneyforward_ex/models/error_model.py
moneyforward_ex/models/ex_destination.py
moneyforward_ex/models/ex_destination_input.py
moneyforward_ex/models/ex_invoice_transaction.py
moneyforward_ex/models/ex_item.py
moneyforward_ex/models/ex_journal.py
moneyforward_ex/models/ex_journal_branch.py
moneyforward_ex/models/ex_journal_branch_side.py
moneyforward_ex/models/ex_office_member_setting.py
moneyforward_ex/models/ex_office_member_setting_input.py
moneyforward_ex/models/ex_report.py
moneyforward_ex/models/ex_report_approval.py
moneyforward_ex/models/ex_report_type.py
moneyforward_ex/models/ex_report_unit.py
moneyforward_ex/models/ex_transaction.py
moneyforward_ex/models/ex_transaction_create_input.py
moneyforward_ex/models/ex_transaction_update_input.py
moneyforward_ex/models/excise.py
moneyforward_ex/models/item.py
moneyforward_ex/models/mf_file.py
moneyforward_ex/models/office.py
